subb/__init__.py
subb/subby.py
subb-1.0.6.dist-info/LICENSE.txt
subb-1.0.6.dist-info/METADATA
subb-1.0.6.dist-info/WHEEL
subb-1.0.6.dist-info/top_level.txt
subb-1.0.6.dist-info/RECORD
