Metadata-Version: 2.1
Name: subb
Version: 1.0.6
Summary: subb is a wrapper for python subprocess module
Home-page: https://github.com/MoserMichael/subb
Author: Michael Moser
Author-email: moser.michael@gmail.com
License: MIT
Keywords: utility
Platform: UNKNOWN
Classifier: Programming Language :: Python :: 3
Classifier: License :: OSI Approved :: MIT License
Classifier: Operating System :: OS Independent
Classifier: Topic :: Text Processing
Requires-Python: >=3.6
